quantregCF/__init__.py
quantregCF/asympt_variance.py
quantregCF/dev_lambda.py
quantregCF/eval_bspline_basis.py
quantregCF/first_reg.py
quantregCF/kernel.py
quantregCF/loaddata.py
quantregCF/quantregCF.py
quantregCF/second_reg.py
src/__init__.py
src/quantregCF/__init__.py
src/quantregCF/asympt_variance.py
src/quantregCF/dev_lambda.py
src/quantregCF/eval_bspline_basis.py
src/quantregCF/first_reg.py
src/quantregCF/kernel.py
src/quantregCF/loaddata.py
src/quantregCF/quantregCF.py
src/quantregCF/second_reg.py
quantregCF-1.0.0.dist-info/LICENSE
quantregCF-1.0.0.dist-info/METADATA
quantregCF-1.0.0.dist-info/WHEEL
quantregCF-1.0.0.dist-info/top_level.txt
quantregCF-1.0.0.dist-info/RECORD
