Metadata-Version: 2.1
Name: quantregCF
Version: 1.0.0
Summary: The control function approach for quantile regression models
Home-page: https://github.com/quantregCF/quantregCF-py
Author: Sokbae (Simon) Lee, Suwijak (Max) Mongkalakorn
Author-email: sl3841@columbia.edu, sm4791@columbia.edu
License: MIT
Platform: UNKNOWN
Classifier: License :: OSI Approved :: MIT License
Classifier: Programming Language :: Python :: 3
Classifier: Programming Language :: Python :: 3.7
License-File: LICENSE
Requires-Dist: numpy
Requires-Dist: pandas
Requires-Dist: scipy
Requires-Dist: cvxpy
